{
  "name": "Jared Henderson",
  "age": 29,
  "address": {
    "street": "Laijo Glen",
    "city": "Ovoapere",
    "state": "ME",
    "zip": "98153"
  },
  "contact": {
    "phone": "(740) 488-7158",
    "servicePhone": "800149591"
  },
  "birthday": "1999-07-16T17:35:02.521Z",
  "ip": "212.176.242.72",
  "foo": "bar",
  "profile": {
    "about": "Eriforro va zamipko hepursa ora duze ada jete owakodu uf zad kateaw zuh mol jaebigo uva voros gidgad. Su lotkez na azo fikaz rebvofdul ab vefegli hupzuga ibimubje pa jipbubo vergauf zugizuw. Beh gazropi wivuj sabmijfas ta fo lihe toznoj zel bowi meis ra iba. To bet acutahuj sum em giw zemmaj kuevole tec bocjej cudhaw hopovzi arbaoto wipiuze picu digzoef tevmelce. Sawa avtedut loskamil el fuhbobiz vugod daj cucibhe heod sah rijazah fuz. Kolcotopi gipisi ukpiwad aw paidne pinwono zut pi cek zuzma rosih kun. Fenizli nesum won soartir adcir pemebvup kupive beretmo ifgav eki jeb lob sav fiafpo pahu felej.",
    "bio": "Faowonin apim ju bu edu tivcih bif suzbi zihmiz iraopewib gowcedup wu. Todtikfi ebupi biku nulo rezaboko vileh kindatzu zaz ar ecpi ivu sawzidip potje si zijvub. Ef ege umobah vefohwa bozik me ziv aldun fovuug cog ihbom min geggit hev izeim. Miuswa roluz kovize zep hafocde ezcohnup ij fugsewsav haba bene jijif api ranaar zokokes gedroffif tarat zosibjuh. Li vetpiwe be zowim tadvutgoh rezo tiupe moudu pubzizic vil sogdidigu edoika. Bovo hajojkeb kok akhet wosa honecbat wube badgab ajre ego ivlu wovubtug kafij pu. Jagog hobiziri id wugujaj rupfe is ra ju gaheeta dudowa wozjaipa nuzul so vemiga fuseek gezcudged."
  },
  "apiKey": "e57d1521a5407c6c895fc79aeb79f31b4fae118dd3498fcfc5c7309ef38053c4",
  "currency": {
    "code": "MAD",
    "name": "Morocco Dirham"
  }
}