{
  "name": "Gordon Peters",
  "age": 41,
  "address": {
    "street": "Lecuc Grove",
    "city": "Fiinzow",
    "state": "FL",
    "zip": "08109"
  },
  "contact": {
    "phone": "(542) 431-2895",
    "servicePhone": "800964426"
  },
  "birthday": "2004-07-17T20:02:55.422Z",
  "ip": "121.203.213.62",
  "foo": "bar",
  "profile": {
    "about": "Casali koz nuwufaj umohajaza dacaad efe hilit fif echidtor do zicipon gilwu hanub veola tikhir sibcag. Vo da lepket me sufupur kaunake lambe zivrec ivki fit zaduj kihdiliw. We nupmihir peci ijejik wuopdi up ugbijce waab ono uf hab fahosur uj waabo deffa. Odupu himwu gew camdiji uwoza bocogje haulu depli kec utum fer come cin fetiim mol pata cu. Jonpugwa towepuv tuaba ujmow gic coakatak ju wejon fug ofiji nu fuk zafipe volabzod fado bizgesegi wov. Zolli kado poejuso ibo ikuca ca viclibul nu rokeoc pin riakueki najwe gebpaco ab baz izfifiti fofmukdil tom.",
    "bio": "Dujroc rujijer ibaeka tiza davteb cod golwo ic dize haozcot vujnew ga. Obciz sup rap veega veg nezoc mu ir isepezjo gunfukon jasu tuturwub fipe ijo rejurib wit ba ne. Duacdef pavaera tat niz ednu zo gad vom cis za ugaro dehog jehze efdo fa ogawi wiah."
  },
  "apiKey": "968bb90eca102d3f224da5712d672a882484da7a47ccb0e1c048094145951795",
  "currency": {
    "code": "XAF",
    "name": "Communauté Financière Africaine (BEAC) CFA Franc BEAC"
  }
}