{
  "name": "Roy Butler",
  "age": 44,
  "address": {
    "street": "Duzla View",
    "city": "Cekgefi",
    "state": "WA",
    "zip": "74913"
  },
  "contact": {
    "phone": "(663) 836-5878",
    "servicePhone": "800286726"
  },
  "birthday": "1975-04-27T18:06:59.466Z",
  "ip": "178.29.91.11",
  "foo": "bar",
  "profile": {
    "about": "Oz acoazo nuptadog low mepi afojuloru buzefzag us ocuima vo holhoges fargaf suzo cagpu. Buudo pow mi ijpew gisi aw mekuchu jiittul ehidoje zoiv sobcuku mezen aso oro rip sekueka. Veavno pelbu came dahzek dep guh ba po he ramojal me wi gokri. Edoah sesle lilena abnu age boremjan fikmitan ve tute etrufep vebab duwa zezizu nekizsuc zuake ihouji ejare bi. Ucado zacefdes wak zouhoho itohub ese zovgafocu peka nelpadub ges vevos dumebzo naconwu irabuiz.",
    "bio": "Ergu umci sajihhiv ufuirciw de otma kopkekoz da zugipi lok fif azbe siv dovvewsoz jungi rik tucucdi. Cerotoro nokaloru lig li defal hujnatro defoope rejoz to sijolope ze timwajavi zatud po. Hajjuna wivup ru tigpabca juf difoal ew vakcijezu liruheg denefa doked olwaci cubu. Ukwuz soltu kiite osi gom ujvi ked nog vetzubo fidso zujruf bode re hir olsecwu ejahol paaf idehonkic."
  },
  "apiKey": "1589a1e02561020158b0ae6fc957e01966f0726066791795e2f72d94bbbea5c0",
  "currency": {
    "code": "CNY",
    "name": "China Yuan Renminbi"
  }
}